{"lastUsed":1642249226862,"path":"C:\/Class\/SSDClass2","projectCount":1,"recentFiles":[{"path":"\/Servers\/Tomcat v8.5 Server at localhost-config","parentWorkspace":"C:\/Class\/SSDClass2","name":"context.xml","lastModified":1641376389000},{"path":"\/ssdPro\/src\/main\/webapp\/main","parentWorkspace":"C:\/Class\/SSDClass2","name":"popup_main.js","lastModified":1642120138000},{"path":"\/ssdPro\/src\/main\/java\/command\/member","parentWorkspace":"C:\/Class\/SSDClass2","name":"JoinOKHandler.java","lastModified":1642122741000},{"path":"\/ssdPro\/src\/main\/java\/command\/notice","parentWorkspace":"C:\/Class\/SSDClass2","name":"NoticeHandler.java","lastModified":1642125985000},{"path":"\/Servers\/Tomcat v8.5 Server at localhost-config","parentWorkspace":"C:\/Class\/SSDClass2","name":"server.xml","lastModified":1641525666000},{"path":"\/Servers\/Tomcat v8.5 Server at localhost-config","parentWorkspace":"C:\/Class\/SSDClass2","name":"web.xml","lastModified":1641376389000},{"path":"\/ssdPro\/src\/main\/webapp","parentWorkspace":"C:\/Class\/SSDClass2","name":"default.jsp","lastModified":1642127265000},{"path":"\/ssdPro\/src\/main\/webapp\/notice","parentWorkspace":"C:\/Class\/SSDClass2","name":"notice.jsp","lastModified":1642139275000},{"path":"\/ssdPro\/src\/main\/webapp\/product","parentWorkspace":"C:\/Class\/SSDClass2","name":"best100.jsp","lastModified":1642246354268},{"path":"\/ssdPro\/src\/main\/webapp\/product","parentWorkspace":"C:\/Class\/SSDClass2","name":"new100_json.jsp","lastModified":1642120415000},{"path":"\/ssdPro\/src\/main\/webapp\/WEB-INF","parentWorkspace":"C:\/Class\/SSDClass2","name":"web.xml","lastModified":1642248144876},{"path":"\/ssdPro\/src\/main\/java\/persistence","parentWorkspace":"C:\/Class\/SSDClass2","name":"MemberDAO.java","lastModified":1642076135000},{"path":"\/Servers\/Tomcat v8.5 Server at localhost-config","parentWorkspace":"C:\/Class\/SSDClass2","name":"tomcat-users.xml","lastModified":1641376389000},{"path":"\/ssdPro\/src\/main\/webapp\/jscript\/join","parentWorkspace":"C:\/Class\/SSDClass2","name":"checkID.js","lastModified":1641810426000},{"path":"\/ssdPro\/src\/main\/java\/persistence","parentWorkspace":"C:\/Class\/SSDClass2","name":"IProduct.java","lastModified":1642245002952,"locationURI":"file:\/C:\/Class\/SSDClass2\/ssdPro\/src\/main\/java\/persistence\/IProduct.java"},{"path":"\/ssdPro\/src\/main\/java\/controller","parentWorkspace":"C:\/Class\/SSDClass2","name":"LoginOK.java","lastModified":1642057893000},{"path":"\/ssdPro\/src\/main\/webapp\/product","parentWorkspace":"C:\/Class\/SSDClass2","name":"giftGoodsList.jsp","lastModified":1642137717000},{"path":"\/ssdPro\/src\/main\/java\/persistence","parentWorkspace":"C:\/Class\/SSDClass2","name":"IOrder.java","lastModified":1642078056000},{"path":"\/ssdPro\/src\/main\/java\/command","parentWorkspace":"C:\/Class\/SSDClass2","name":"NullHandler.java","lastModified":1642120741000},{"path":"\/ssdPro\/src\/main\/java\/command\/notice","parentWorkspace":"C:\/Class\/SSDClass2","name":"CsCenterHandler.java","lastModified":1642126076000},{"path":"\/ssdPro\/src\/main\/webapp\/layout","parentWorkspace":"C:\/Class\/SSDClass2","name":"left_wrap_size.jsp","lastModified":1642078223000},{"path":"\/ssdPro\/src\/main\/java\/persistence","parentWorkspace":"C:\/Class\/SSDClass2","name":"ProductDAO.java","lastModified":1642244951422},{"path":"\/ssdPro\/src\/main\/java\/service","parentWorkspace":"C:\/Class\/SSDClass2","name":"ProductService.java","lastModified":1642124658000},{"path":"\/ssdPro\/src\/main\/webapp\/data\/sungsimdang\/css","parentWorkspace":"C:\/Class\/SSDClass2","name":"common.css","lastModified":1642121366000},{"path":"\/ssdPro\/src\/main\/java\/controller","parentWorkspace":"C:\/Class\/SSDClass2","name":"Logout.java","lastModified":1642122408000},{"path":"\/ssdPro\/src\/main\/webapp\/cscenter","parentWorkspace":"C:\/Class\/SSDClass2","name":"cscenter.jsp","lastModified":1642123104000},{"path":"\/ssdPro\/src\/main\/java\/domain","parentWorkspace":"C:\/Class\/SSDClass2","name":"Order.java","lastModified":1642077325000},{"path":"\/ssdPro\/src\/main\/webapp","parentWorkspace":"C:\/Class\/SSDClass2","name":"commandHandler.properties","lastModified":1642247007165},{"path":"\/ssdPro\/src\/main\/webapp","parentWorkspace":"C:\/Class\/SSDClass2","name":"default.asp","lastModified":1642120555000},{"path":"\/Servers\/Tomcat v8.5 Server at localhost-config","parentWorkspace":"C:\/Class\/SSDClass2","name":"catalina.properties","lastModified":1641376389000},{"path":"\/ssdPro\/src\/main\/webapp\/jscript","parentWorkspace":"C:\/Class\/SSDClass2","name":"categoryMenu.js","lastModified":1642121031000},{"path":"\/ssdPro\/src\/main\/java\/command","parentWorkspace":"C:\/Class\/SSDClass2","name":"ProductHandler.java","lastModified":1642244811618},{"path":"\/ssdPro\/src\/main\/java\/persistence\/manager","parentWorkspace":"C:\/Class\/SSDClass2","name":"ProdDAO.java","lastModified":1642247895496,"locationURI":"file:\/C:\/Class\/SSDClass2\/ssdPro\/src\/main\/java\/persistence\/manager\/ProdDAO.java"},{"path":"\/ssdPro\/src\/main\/java\/command\/product","parentWorkspace":"C:\/Class\/SSDClass2","name":"BestHandler.java","lastModified":1642120760000},{"path":"\/ssdPro\/src\/main\/java\/command\/member","parentWorkspace":"C:\/Class\/SSDClass2","name":"LoginHandler.java","lastModified":1641522057000},{"path":"\/ssdPro\/src\/main\/webapp\/manager\/product","parentWorkspace":"C:\/Class\/SSDClass2","name":"productlist.jsp","lastModified":1642248147070,"locationURI":"file:\/C:\/Class\/SSDClass2\/ssdPro\/src\/main\/webapp\/manager\/product\/productlist.jsp"},{"path":"\/ssdPro\/src\/main\/webapp","parentWorkspace":"C:\/Class\/SSDClass2","name":"ifrm_popupLayer.jsp","lastModified":1642120595000},{"path":"\/ssdPro\/src\/main\/webapp\/my","parentWorkspace":"C:\/Class\/SSDClass2","name":"order_total.jsp","lastModified":1642137779000},{"path":"\/ssdPro\/src\/main\/webapp\/layout","parentWorkspace":"C:\/Class\/SSDClass2","name":"util_wrap.jsp","lastModified":1642247526595},{"path":"\/ssdPro\/src\/main\/webapp\/notice","parentWorkspace":"C:\/Class\/SSDClass2","name":"noticeFaq.jsp","lastModified":1642139008000},{"path":"\/ssdPro\/src\/main\/webapp\/notice","parentWorkspace":"C:\/Class\/SSDClass2","name":"main.jsp","lastModified":1642125590000},{"path":"\/ssdPro\/src\/main\/webapp\/member","parentWorkspace":"C:\/Class\/SSDClass2","name":"join.jsp","lastModified":1642123104000},{"path":"\/ssdPro\/src\/main\/java\/domain","parentWorkspace":"C:\/Class\/SSDClass2","name":"ProductDTO.java","lastModified":1642124808000},{"path":"\/ssdPro\/src\/main\/java\/command","parentWorkspace":"C:\/Class\/SSDClass2","name":"CommandHandler.java","lastModified":1641521315000},{"path":"\/ssdPro\/src\/main\/webapp\/notice","parentWorkspace":"C:\/Class\/SSDClass2","name":"noticeAsk.jsp","lastModified":1642141003000},{"path":"\/ssdPro\/src\/main\/java\/command\/product","parentWorkspace":"C:\/Class\/SSDClass2","name":"DeliveryHandler.java","lastModified":1642120760000},{"path":"\/ssdPro\/src\/main\/java\/controller","parentWorkspace":"C:\/Class\/SSDClass2","name":"DispatcherServlet.java","lastModified":1642042504000},{"path":"\/ssdPro\/src\/main\/webapp\/product","parentWorkspace":"C:\/Class\/SSDClass2","name":"best100_json.jsp","lastModified":1642246257810},{"path":"\/ssdPro\/src\/main\/webapp\/cscenter","parentWorkspace":"C:\/Class\/SSDClass2","name":"consultReg.jsp","lastModified":1642123104000},{"path":"\/ssdPro\/src\/main\/java\/command\/notice","parentWorkspace":"C:\/Class\/SSDClass2","name":"NoticeCacaoHandler.java","lastModified":1642125985000},{"path":"\/ssdPro\/src\/main\/webapp\/my","parentWorkspace":"C:\/Class\/SSDClass2","name":"main.jsp","lastModified":1641810426000},{"path":"\/ssdPro\/src\/main\/java\/controller","parentWorkspace":"C:\/Class\/SSDClass2","name":"IdCheck.java","lastModified":1641880720000},{"path":"\/ssdPro\/src\/main\/java\/domain","parentWorkspace":"C:\/Class\/SSDClass2","name":"Member.java","lastModified":1642075057000},{"path":"\/ssdPro\/src\/main\/java\/persistence","parentWorkspace":"C:\/Class\/SSDClass2","name":"IMember.java","lastModified":1642075508000},{"path":"\/ssdPro\/src\/main\/java\/command","parentWorkspace":"C:\/Class\/SSDClass2","name":"DefaultHandler.java","lastModified":1642124991000},{"path":"\/ssdPro\/src\/main\/java\/command\/product","parentWorkspace":"C:\/Class\/SSDClass2","name":"ListHandler.java","lastModified":1642120761000},{"path":"\/ssdPro\/src\/main\/webapp\/product","parentWorkspace":"C:\/Class\/SSDClass2","name":"content.jsp","lastModified":1642248941061,"locationURI":"file:\/C:\/Class\/SSDClass2\/ssdPro\/src\/main\/webapp\/product\/content.jsp"},{"path":"\/ssdPro\/src\/main\/webapp\/product","parentWorkspace":"C:\/Class\/SSDClass2","name":"deliveryList.jsp","lastModified":1642137657000},{"path":"\/ssdPro\/src\/main\/webapp\/member","parentWorkspace":"C:\/Class\/SSDClass2","name":"login.jsp","lastModified":1642122266000},{"path":"\/ssdPro\/src\/main\/java\/persistence","parentWorkspace":"C:\/Class\/SSDClass2","name":"OrderDAO.java","lastModified":1642078574000},{"path":"\/ssdPro\/src\/main\/java\/command\/notice","parentWorkspace":"C:\/Class\/SSDClass2","name":"NoticeAskHandler.java","lastModified":1642141768000},{"path":"\/ssdPro\/src\/main\/java\/command\/my","parentWorkspace":"C:\/Class\/SSDClass2","name":"OrderHandler.java","lastModified":1642078224000},{"path":"\/ssdPro\/src\/main\/java\/command\/dummy","parentWorkspace":"C:\/Class\/SSDClass2","name":"DummyHandler.java","lastModified":1642138348000},{"path":"\/ssdPro\/src\/main\/java\/command\/member","parentWorkspace":"C:\/Class\/SSDClass2","name":"LoginOKHandler.java","lastModified":1642058488000},{"path":"\/ssdPro\/src\/main\/java\/command\/notice","parentWorkspace":"C:\/Class\/SSDClass2","name":"NoticeFaqHandler.java","lastModified":1642125985000},{"path":"\/ssdPro\/src\/main\/java\/command","parentWorkspace":"C:\/Class\/SSDClass2","name":"ListHandler.java","lastModified":1642124091000},{"path":"\/ssdPro\/src\/main\/webapp\/notice","parentWorkspace":"C:\/Class\/SSDClass2","name":"cscenter.jsp","lastModified":1642139318000},{"path":"\/ssdPro\/src\/main\/java\/persistence","parentWorkspace":"C:\/Class\/SSDClass2","name":"ProductDAOImpl.java","lastModified":1642124316000},{"path":"\/ssdPro\/src\/main\/webapp\/member","parentWorkspace":"C:\/Class\/SSDClass2","name":"regist_agree.jsp","lastModified":1642123104000}]}